pymarshaler/__init__.py
pymarshaler/arg_delegates.py
pymarshaler/errors.py
pymarshaler/marshal.py
pymarshaler/utils.py
pymarshaler-0.4.2.dist-info/METADATA
pymarshaler-0.4.2.dist-info/WHEEL
pymarshaler-0.4.2.dist-info/top_level.txt
pymarshaler-0.4.2.dist-info/RECORD
