Metadata-Version: 2.1
Name: pymarshaler
Version: 0.4.2
Summary: Package to marshal and unmarshal python objects
Home-page: https://github.com/hgromer/pymarshaler
Author: Hernan Romer
Author-email: nanug33@gmail.com
License: UNKNOWN
Platform: UNKNOWN
Classifier: Programming Language :: Python :: 3
Classifier: License :: OSI Approved :: MIT License
Classifier: Operating System :: OS Independent
Requires-Python: >=3.7
Requires-Dist: python-dateutil
Requires-Dist: setuptools
Requires-Dist: orjson
